char2image/__init__.py
char2image/__main__.py
char2image/char2image.py
char2image/chars2images_main.py
char2image-0.0.3.dist-info/DESCRIPTION.rst
char2image-0.0.3.dist-info/METADATA
char2image-0.0.3.dist-info/RECORD
char2image-0.0.3.dist-info/WHEEL
char2image-0.0.3.dist-info/entry_points.txt
char2image-0.0.3.dist-info/metadata.json
char2image-0.0.3.dist-info/top_level.txt
