Metadata-Version: 2.0
Name: char2image
Version: 0.0.3
Summary: Creates a dictionary of character to font image in JSON format.
Home-page: https://github.com/raviqqe/char2image.py/
Author: Yota Toyama
Author-email: raviqqe@gmail.com
License: Public Domain
Platform: UNKNOWN
Classifier: Development Status :: 3 - Alpha
Classifier: Intended Audience :: Developers
Classifier: License :: Public Domain
Classifier: Programming Language :: Python :: 3.4
Classifier: Programming Language :: Python :: 3.5
Classifier: Programming Language :: Python :: 3.6
Classifier: Topic :: Text Processing :: Fonts
Requires-Dist: numpy
Requires-Dist: pillow
